LICENSE
MANIFEST.in
README.rst
setup.cfg
setup.py
stellar_sdk/__init__.py
stellar_sdk/__version__.py
stellar_sdk/account.py
stellar_sdk/asset.py
stellar_sdk/base_server.py
stellar_sdk/base_transaction_envelope.py
stellar_sdk/decorated_signature.py
stellar_sdk/exceptions.py
stellar_sdk/fee_bump_transaction.py
stellar_sdk/fee_bump_transaction_envelope.py
stellar_sdk/helpers.py
stellar_sdk/keypair.py
stellar_sdk/ledger_bounds.py
stellar_sdk/liquidity_pool_asset.py
stellar_sdk/liquidity_pool_id.py
stellar_sdk/memo.py
stellar_sdk/muxed_account.py
stellar_sdk/network.py
stellar_sdk/preconditions.py
stellar_sdk/price.py
stellar_sdk/py.typed
stellar_sdk/signer.py
stellar_sdk/signer_key.py
stellar_sdk/strkey.py
stellar_sdk/time_bounds.py
stellar_sdk/transaction.py
stellar_sdk/transaction_builder.py
stellar_sdk/transaction_envelope.py
stellar_sdk/utils.py
stellar_sdk/operation/__init__.py
stellar_sdk/operation/account_merge.py
stellar_sdk/operation/allow_trust.py
stellar_sdk/operation/begin_sponsoring_future_reserves.py
stellar_sdk/operation/bump_sequence.py
stellar_sdk/operation/change_trust.py
stellar_sdk/operation/claim_claimable_balance.py
stellar_sdk/operation/clawback.py
stellar_sdk/operation/clawback_claimable_balance.py
stellar_sdk/operation/create_account.py
stellar_sdk/operation/create_claimable_balance.py
stellar_sdk/operation/create_passive_sell_offer.py
stellar_sdk/operation/end_sponsoring_future_reserves.py
stellar_sdk/operation/inflation.py
stellar_sdk/operation/liquidity_pool_deposit.py
stellar_sdk/operation/liquidity_pool_withdraw.py
stellar_sdk/operation/manage_buy_offer.py
stellar_sdk/operation/manage_data.py
stellar_sdk/operation/manage_sell_offer.py
stellar_sdk/operation/operation.py
stellar_sdk/operation/path_payment_strict_receive.py
stellar_sdk/operation/path_payment_strict_send.py
stellar_sdk/operation/payment.py
stellar_sdk/operation/revoke_sponsorship.py
stellar_sdk/operation/set_options.py
stellar_sdk/operation/set_trust_line_flags.py
stellar_sdk_mini.egg-info/PKG-INFO
stellar_sdk_mini.egg-info/SOURCES.txt
stellar_sdk_mini.egg-info/dependency_links.txt
stellar_sdk_mini.egg-info/requires.txt
stellar_sdk_mini.egg-info/top_level.txt