Metadata-Version: 2.1
Name: stellar-sdk-mini
Version: 8.2.0.post3
Summary: The Python Stellar SDK library provides APIs to build transactions and connect to Horizon.
Home-page: https://github.com/StellarCN/py-stellar-base
Author: Eno, overcat
Author-email: appweb.cn@gmail.com, 4catcode@gmail.com
License: Apache License 2.0
Project-URL: Documentation, https://stellar-sdk.readthedocs.org
Project-URL: Code, https://github.com/StellarCN/py-stellar-base
Project-URL: Issue tracker, https://github.com/StellarCN/py-stellar-base/issues
Keywords: stellar-sdk,stellar.org,lumens,xlm,blockchain,distributed exchange,cryptocurrency,dex,stellar-core,horizon,sdex,trading
Platform: UNKNOWN
Classifier: Development Status :: 5 - Production/Stable
Classifier: Intended Audience :: Developers
Classifier: Natural Language :: English
Classifier: Operating System :: OS Independent
Classifier: License :: OSI Approved :: Apache Software License
Classifier: Programming Language :: Python
Classifier: Programming Language :: Python :: 3 :: Only
Classifier: Programming Language :: Python :: Implementation :: CPython
Classifier: Programming Language :: Python :: Implementation :: PyPy
Classifier: Topic :: Software Development :: Libraries :: Python Modules
Classifier: Typing :: Typed
Requires-Python: >=3.7.0
License-File: LICENSE
